s04utils/__init__.py
s04utils/modules/__init__.py
s04utils/modules/analyze/HMM_analysis.py
s04utils/modules/analyze/__init__.py
s04utils/modules/analyze/blob_detection.py
s04utils/modules/analyze/dwelltime_analyzer.py
s04utils/modules/analyze/dwelltime_analyzer_v2.py
s04utils/modules/analyze/ld_analyzer.py
s04utils/modules/analyze/pd_hist_utils.py
s04utils/modules/analyze/preprocessing.py
s04utils/modules/load/BinnedTimestamps.py
s04utils/modules/load/Timestamps.py
s04utils/modules/load/__init__.py
s04utils/modules/load/h5.py
s04utils/modules/load/image.py
s04utils/modules/visualize/__init__.py
s04utils/modules/visualize/plot.py
s04utils/modules/visualize/report.py
s04utils-0.1.15.dist-info/LICENSE.txt
s04utils-0.1.15.dist-info/METADATA
s04utils-0.1.15.dist-info/WHEEL
s04utils-0.1.15.dist-info/dependency_links.txt
s04utils-0.1.15.dist-info/top_level.txt
s04utils-0.1.15.dist-info/RECORD
