Metadata-Version: 2.1
Name: s04utils
Version: 0.1.15
Summary: A module to load and analyze timestamp data from HDF5-photon files
Home-page: https://github.com/JKL453/s04-utils
Author: Janosch Kappel
Author-email: jkl453@posteo.de
Classifier: Programming Language :: Python :: 3
Classifier: License :: OSI Approved :: MIT License
Classifier: Operating System :: OS Independent
Requires-Python: >=3.6
License-File: LICENSE.txt
Requires-Dist: h5py
Requires-Dist: numpy
Requires-Dist: scipy ==1.11.2
Requires-Dist: pandas
Requires-Dist: matplotlib
Requires-Dist: scikit-image
Requires-Dist: pillow
Requires-Dist: tabulate
Requires-Dist: sfHMM
Requires-Dist: bokeh
Requires-Dist: pybaselines
Requires-Dist: scipy
Requires-Dist: seaborn
Requires-Dist: fpdf
Requires-Dist: tqdm
Requires-Dist: reportlab
